<?xml version="1.0" encoding="utf-8" ?><dwsync><file name=".DS_Store" server="touchersp.toucher.com.tw" local="3545264182" remote="318763443938178612" Dst="-1" /><file name="icon_step_4.png" server="touchersp.toucher.com.tw" local="3545108162" remote="318763443938178612" Dst="-1" /><file name="icon_step_5.png" server="touchersp.toucher.com.tw" local="3545108168" remote="318763443938499432" Dst="-1" /><file name="icon_step_6.png" server="touchersp.toucher.com.tw" local="3545108172" remote="318763443938499432" Dst="-1" /><file name="cover_image.png" server="touchersp.toucher.com.tw" local="3545263762" remote="318763443938499432" Dst="-1" /><file name="point_bg.jpg" server="touchersp.toucher.com.tw" local="3545107874" remote="318763443938499432" Dst="-1" /><file name="point_head_1.png" server="touchersp.toucher.com.tw" local="3545263810" remote="318763443938178612" Dst="-1" /><file name="point_head_2.png" server="touchersp.toucher.com.tw" local="3545108118" remote="318763443938178612" Dst="-1" /><file name="point_icon_1.png" server="touchersp.toucher.com.tw" local="3545263538" remote="318763443938499432" Dst="-1" /><file name="point_icon_2.png" server="touchersp.toucher.com.tw" local="3545263530" remote="318763443938499432" Dst="-1" /><file name="point_phone_1.png" server="touchersp.toucher.com.tw" local="3545108126" remote="318763443938178612" Dst="-1" /><file name="point_phone_3.png" server="touchersp.toucher.com.tw" local="3545108136" remote="318763443938499432" Dst="-1" /><file name="point_phone_2.png" server="touchersp.toucher.com.tw" local="3545108130" remote="318763443938499432" Dst="-1" /><file name="point_phone_4.png" server="touchersp.toucher.com.tw" local="3545108142" remote="318763443938499432" Dst="-1" /><file name="point_phone_5.png" server="touchersp.toucher.com.tw" local="3545108148" remote="318763443938499432" Dst="-1" /><file name="point_phone_6.png" server="touchersp.toucher.com.tw" local="3545108152" remote="318763443938499432" Dst="-1" /></dwsync>